LICENSE
README.md
setup.cfg
setup.py
velenium/__init__.py
velenium.egg-info/PKG-INFO
velenium.egg-info/SOURCES.txt
velenium.egg-info/dependency_links.txt
velenium.egg-info/requires.txt
velenium.egg-info/top_level.txt