Metadata-Version: 2.1
Name: velenium
Version: 0.7.0
Summary: Interact with an app using visual definitions of elements
Home-page: https://github.com/manzanero/velenium
Download-URL: https://github.com/manzanero/velenium/archive/refs/tags/v0.7.0.tar.gz
Author: Alejandro Manzanero Sobrado
Author-email: alejmans@gmail.com
License: MIT
Keywords: visual,testing,selenium,appium,desktop
Classifier: Development Status :: 4 - Beta
Classifier: Intended Audience :: Developers
Classifier: Topic :: Software Development :: Build Tools
Classifier: License :: OSI Approved :: MIT License
Classifier: Programming Language :: Python :: 3.9
License-File: LICENSE
Requires-Dist: opencv-python
Requires-Dist: Pillow
Requires-Dist: imutils
Requires-Dist: numpy
Requires-Dist: Appium-Python-Client
Requires-Dist: selenium
Provides-Extra: docs
Requires-Dist: mkdocs==1.2.*; extra == "docs"
